sqlow/__init__.py
sqlow/py.typed
sqlow-0.2.0.dist-info/METADATA
sqlow-0.2.0.dist-info/WHEEL
sqlow-0.2.0.dist-info/licenses/LICENSE
sqlow-0.2.0.dist-info/RECORD
