Metadata-Version: 2.4
Name: sqlow
Version: 0.2.0
Summary: Dataclass-native SQLite.
Author-email: hlop3z <23062270+hlop3z@users.noreply.github.com>
License-File: LICENSE
Requires-Python: >=3.12
